ethnicolr/__init__.py
ethnicolr/census_ln.py
ethnicolr/cli.py
ethnicolr/data/__init__.py
ethnicolr/data/census/__init__.py
ethnicolr/data/census/census_2000.csv
ethnicolr/data/census/census_2010.csv
ethnicolr/data/census/census_hispanic_ln.csv
ethnicolr/data/census/readme.md
ethnicolr/data/fl_voter_reg/README.md
ethnicolr/data/fl_voter_reg/__init__.py
ethnicolr/data/nc_voter_reg/README.md
ethnicolr/data/nc_voter_reg/__init__.py
ethnicolr/data/wiki/__init__.py
ethnicolr/data/wiki/readme.md
ethnicolr/data/wiki/wiki_name_race.csv
ethnicolr/download.py
ethnicolr/ethnicolr_class.py
ethnicolr/model_base.py
ethnicolr/models/README.md
ethnicolr/models/__init__.py
ethnicolr/models/census/__init__.py
ethnicolr/models/census/lstm/__init__.py
ethnicolr/models/census/lstm/census2000_ln_lstm.h5
ethnicolr/models/census/lstm/census2000_ln_vocab.csv
ethnicolr/models/census/lstm/census2000_race.csv
ethnicolr/models/census/lstm/census2010_ln_lstm.h5
ethnicolr/models/census/lstm/census2010_ln_vocab.csv
ethnicolr/models/census/lstm/census2010_race.csv
ethnicolr/models/fl_voter_reg/__init__.py
ethnicolr/models/fl_voter_reg/lstm/__init__.py
ethnicolr/models/fl_voter_reg/lstm/fl_all_fullname_lstm_5_cat.h5
ethnicolr/models/fl_voter_reg/lstm/fl_all_fullname_lstm_5_cat_2022.h5
ethnicolr/models/fl_voter_reg/lstm/fl_all_fullname_vocab_5_cat.csv
ethnicolr/models/fl_voter_reg/lstm/fl_all_fullname_vocab_5_cat_2022.csv
ethnicolr/models/fl_voter_reg/lstm/fl_all_ln_lstm.h5
ethnicolr/models/fl_voter_reg/lstm/fl_all_ln_lstm_5_cat.h5
ethnicolr/models/fl_voter_reg/lstm/fl_all_ln_lstm_5_cat_2022.h5
ethnicolr/models/fl_voter_reg/lstm/fl_all_ln_vocab.csv
ethnicolr/models/fl_voter_reg/lstm/fl_all_ln_vocab_5_cat.csv
ethnicolr/models/fl_voter_reg/lstm/fl_all_ln_vocab_5_cat_2022.csv
ethnicolr/models/fl_voter_reg/lstm/fl_all_name_lstm.h5
ethnicolr/models/fl_voter_reg/lstm/fl_all_name_vocab.csv
ethnicolr/models/fl_voter_reg/lstm/fl_ln_five_cat_race.csv
ethnicolr-0.21.1.dist-info/WHEEL
ethnicolr-0.21.1.dist-info/entry_points.txt
ethnicolr-0.21.1.dist-info/METADATA
ethnicolr-0.21.1.dist-info/RECORD
