Metadata-Version: 2.4
Name: ethnicolr
Version: 0.21.1
Summary: Modern ML library for race/ethnicity prediction from names with intuitive CLI
Keywords: race,ethnicity,names,demographics,machine-learning,nlp
Author: Gaurav Sood, Suriyan Laohaprapanon
Author-email: Gaurav Sood <contact@gsood.com>, Suriyan Laohaprapanon <suriyant@gmail.com>
License-Expression: MIT
Classifier: Development Status :: 5 - Production/Stable
Classifier: Intended Audience :: Developers
Classifier: Intended Audience :: Science/Research
Classifier: Topic :: Scientific/Engineering :: Information Analysis
Classifier: Topic :: Software Development :: Libraries :: Python Modules
Classifier: Topic :: Utilities
Classifier: Programming Language :: Python
Classifier: Programming Language :: Python :: 3
Classifier: Programming Language :: Python :: 3.11
Requires-Dist: pandas>=2.2.0
Requires-Dist: numpy>=1.26.0,<2.0.0
Requires-Dist: click>=8.0.0
Requires-Dist: pytest>=7.0 ; extra == 'dev'
Requires-Dist: pytest-cov>=4.0 ; extra == 'dev'
Requires-Dist: pytest-xdist>=3.0 ; extra == 'dev'
Requires-Dist: ruff>=0.7.0 ; extra == 'dev'
Requires-Dist: mypy>=1.0 ; extra == 'dev'
Requires-Dist: pre-commit>=3.0 ; extra == 'dev'
Requires-Dist: sphinx>=7.0 ; extra == 'docs'
Requires-Dist: furo>=2024.1.29 ; extra == 'docs'
Requires-Dist: sphinx-autodoc-typehints>=1.25 ; extra == 'docs'
Requires-Dist: sphinx-copybutton>=0.5 ; extra == 'docs'
Requires-Dist: myst-parser>=2.0 ; extra == 'docs'
Requires-Dist: nbsphinx>=0.9.0 ; extra == 'docs'
Requires-Dist: pandoc>=2.0 ; extra == 'docs'
Requires-Dist: ipykernel>=6.0 ; extra == 'docs'
Requires-Dist: ipython>=8.0.0 ; extra == 'docs'
Requires-Dist: matplotlib>=3.5.0 ; extra == 'docs'
Requires-Dist: tensorflow>=2.15.0,<3.0.0 ; sys_platform != 'win32' and extra == 'inference'
Requires-Dist: tensorflow-intel>=2.15.0,<3.0.0 ; sys_platform == 'win32' and extra == 'inference'
Requires-Dist: protobuf>=4.21.0,<7.0.0 ; extra == 'inference'
Requires-Dist: typing-extensions>=4.4,<5.0 ; extra == 'inference'
Requires-Dist: pytest>=7.0 ; extra == 'test'
Requires-Dist: pytest-cov>=4.0 ; extra == 'test'
Requires-Dist: pytest-xdist>=3.0 ; extra == 'test'
Requires-Python: >=3.11, <3.13
Project-URL: Bug Reports, https://github.com/appeler/ethnicolr/issues
Project-URL: Documentation, https://appeler.github.io/ethnicolr/
Project-URL: Homepage, https://github.com/appeler/ethnicolr
Project-URL: Source Code, https://github.com/appeler/ethnicolr
Provides-Extra: dev
Provides-Extra: docs
Provides-Extra: inference
Provides-Extra: test
